[
    {
        "name": {
            "name": "花家院子",
            "content": "一个温馨的院子，充满了家庭的温暖。院子中央有一棵大树，树下放着一张石桌和几张石凳。"
        },
        "url": ""
    },
    {
        "name": {
            "name": "军营",
            "content": "一个简陋但整洁的军营，帐篷整齐排列，士兵们正在进行日常训练。"
        },
        "url": ""
    },
    {
        "name": {
            "name": "训练场",
            "content": "一个宽阔的训练场，地面上铺满了沙土，周围摆放着各种训练器材。"
        },
        "url": ""
    },
    {
        "name": {
            "name": "战场",
            "content": "一个激烈的战场，硝烟弥漫，士兵们在奋力厮杀。"
        },
        "url": ""
    },
    {
        "name": {
            "name": "军帐",
            "content": "一个简陋的军帐，里面摆放着地图和作战计划，气氛紧张。"
        },
        "url": ""
    },
    {
        "name": {
            "name": "花家院子",
            "content": "一个温馨的院子，充满了家庭的温暖。院子中央有一棵大树，树下放着一张石桌和几张石凳。"
        },
        "url": ""
    },
    {
        "name": {
            "name": "皇宫",
            "content": "一个庄严的皇宫，金碧辉煌，皇帝坐在高高的宝座上，周围站满了文武百官。"
        },
        "url": ""
    }
]