[
    {
        "name": "花木兰",
        "content": "一个聪明勇敢的年轻女子，为了替年迈的父亲从军，她伪装成男人，展现出卓越的军事才能和领导能力。",
        "per": "标准女音"
    },
    {
        "name": "花弧",
        "content": "花木兰的父亲，年事已高，身体虚弱，但曾是一位勇敢的战士，深知战场的残酷。",
        "per": "标准男音"
    },
    {
        "name": "刘元帅",
        "content": "军队的统帅，严厉但公正，欣赏花木兰的才干，不知其真实身份。",
        "per": "标准男音"
    },
    {
        "name": "李将军",
        "content": "花木兰的战友和朋友，性格豪爽，重情重义，逐渐怀疑花木兰的身份。",
        "per": "标准男音"
    },
    {
        "name": "香兰",
        "content": "花木兰的好友，温柔善良，是木兰的精神支柱，支持她的决定并帮助她隐藏身份。",
        "per": "标准女音"
    },
    {
        "name": "皇帝",
        "content": "国家的最高统治者，英明神武，最终发现花木兰的真实身份并赐予她荣誉。",
        "per": "标准男音"
    }
]